{
  "categories": {
    "Flowchart": "Flowchart",
    "SequenceDiagram": "SequenceDiagram",
    "ClassDiagram": "ClassDiagram",
    "StateDiagram": "StateDiagram",
    "EntityRelationshipDiagram": "EntityRelationshipDiagram",
    "UserJourneyDiagram": "UserJourneyDiagram",
    "GanttChart": "GanttChart",
    "PieChart": "PieChart",
    "RequirementDiagram": "RequirementDiagram",
    "GitGraph": "GitGraph"
  },
  "elements": [
    {
      "id": "ccdd6bbe-60c7-49e1-b871-49f6575b48ec",
      "category": "Flowchart",
      "description": "a simple flowchart with top to down direction",
      "content": "flowchart TD\nStart --> Stop",
      "sortingOrder": 1,
      "isPinned": false
    },
    {
      "id": "16546cca-2da9-4618-a182-c5adb61b2b8b",
      "category": "Flowchart",
      "description": "a simple flowchart with left to right direction",
      "content": "flowchart LR\nStart --> Stop",
      "sortingOrder": 2,
      "isPinned": false
    },
    {
      "id": "493f93c8-2aa1-4325-bc48-448dd04b0709",
      "category": "Flowchart",
      "description": "A node with round edges",
      "content": "id1(Some text)",
      "sortingOrder": 3,
      "isPinned": false
    },
    {
      "id": "336e5e6b-362a-47ce-b3df-a0a503c3cf27",
      "category": "Flowchart",
      "description": "A stadium-shaped node",
      "content": "id1([Some text])",
      "sortingOrder": 4,
      "isPinned": false
    },
    {
      "id": "c3c2a5a5-fb2e-41c1-bef0-32f94585d3b9",
      "category": "Flowchart",
      "description": "A node in a cylindrical shape",
      "content": "id1[(Database)]",
      "sortingOrder": 5,
      "isPinned": false
    },
    {
      "id": "cf26308d-838e-4ebe-8e2f-3b4b400fedd5",
      "category": "Flowchart",
      "description": "A node in the form of a circle",
      "content": "id1((Some text))",
      "sortingOrder": 6,
      "isPinned": false
    },
    {
      "id": "b2a542b6-355e-40db-a667-d01a3fbcd386",
      "category": "Flowchart",
      "description": "A node (rhombus)",
      "content": "id1{Some text}",
      "sortingOrder": 7,
      "isPinned": false
    },
    {
      "id": "2f13293c-150f-4b17-83b7-69225ef9340b",
      "category": "Flowchart",
      "description": "A link with arrow head",
      "content": "A-->B",
      "sortingOrder": 8,
      "isPinned": false
    },
    {
      "id": "bd263684-1cfc-4b31-95e9-a25bab95c9ef",
      "category": "Flowchart",
      "description": "An open link",
      "content": "A --- B",
      "sortingOrder": 9,
      "isPinned": false
    },
    {
      "id": "bb4ec9b0-a65a-44aa-a209-7909416777ec",
      "category": "Flowchart",
      "description": "Text on links",
      "content": "A-- This is the text! ---B",
      "sortingOrder": 10,
      "isPinned": false
    },
    {
      "id": "4cf14488-08e2-4512-a713-f05b6647edeb",
      "category": "Flowchart",
      "description": "A link with arrow head and text",
      "content": "A-->|text|B",
      "sortingOrder": 11,
      "isPinned": false
    },
    {
      "id": "2752bb3e-ec63-4ce6-9ed7-9297925d1ef0",
      "category": "Flowchart",
      "description": "Dotted link",
      "content": "A-.->B",
      "sortingOrder": 12,
      "isPinned": false
    },
    {
      "id": "f71015a5-97eb-4ed3-8e7e-15119e295494",
      "category": "Flowchart",
      "description": "Thick link",
      "content": "A ==> B",
      "sortingOrder": 13,
      "isPinned": false
    },
    {
      "id": "69390b57-627f-4b97-9cb0-cc257dd3d3e0",
      "category": "Flowchart",
      "description": "Subgraph",
      "content": "subgraph one\na1-->a2\nend",
      "sortingOrder": 14,
      "isPinned": false
    },
    {
      "id": "b344d438-a2a4-4178-bceb-4c436d17cf43",
      "category": "SequenceDiagram",
      "description": "a simple sequence diagram",
      "content": "sequenceDiagram\nAlice->>John: Hello John, how are you?\nJohn-->>Alice: Great!\nAlice-)John: See you later!",
      "sortingOrder": 0,
      "isPinned": false
    },
    {
      "id": "3a87d498-32b8-4624-96da-ad8eb3e43bfa",
      "category": "SequenceDiagram",
      "description": "a simple sequence diagram with actors",
      "content": "sequenceDiagram\nactor Alice\nactor John\nAlice->>John: Hello John, how are you?\nJohn-->>Alice: Great!\nAlice-)John: See you later!",
      "sortingOrder": 1,
      "isPinned": false
    },
    {
      "id": "878038a2-ca27-4035-a144-272ca59caa3e",
      "category": "ClassDiagram",
      "description": "sample class",
      "content": "class Duck{\n            +String beakColor\n            +swim()\n            +quack()\n        }",
      "sortingOrder": 0,
      "isPinned": false
    },
    {
      "id": "84c05c2c-947a-4801-9f8e-76b1eaeccc6c",
      "category": "ClassDiagram",
      "description": "sample class",
      "content": "class BankAccount\n        BankAccount : +String owner\n        BankAccount : +Bigdecimal balance\n        BankAccount : +deposit(amount)\n        BankAccount : +withdrawal(amount)",
      "sortingOrder": 1,
      "isPinned": false
    },
    {
      "id": "6d584f5a-7610-4688-9f32-89206ded475a",
      "category": "ClassDiagram",
      "description": "generic class",
      "content": "class Square~Shape~{\n            int id\n            List~int~ position\n            setPoints(List~int~ points)\n            getPoints() List~int~\n        }\n        \n        Square : -List~string~ messages\n        Square : +setMessages(List~string~ messages)\n        Square : +getMessages() List~string~",
      "sortingOrder": 2,
      "isPinned": false
    },
    {
      "id": "9f441853-55bc-4c8b-b083-93eb571f361c",
      "category": "ClassDiagram",
      "description": "inheritance",
      "content": "classA <|-- classB",
      "sortingOrder": 3,
      "isPinned": false
    },
    {
      "id": "42fa605f-cd09-4585-91b1-40be3abae306",
      "category": "ClassDiagram",
      "description": "composition",
      "content": "classC *-- classD",
      "sortingOrder": 4,
      "isPinned": false
    },
    {
      "id": "240b76de-5bc7-44b7-855d-fe331d0d5d2f",
      "category": "ClassDiagram",
      "description": "aggregation",
      "content": "classE o-- classF",
      "sortingOrder": 5,
      "isPinned": false
    },
    {
      "id": "ce84ab7b-93fc-4cc5-893e-b8bc1496c13b",
      "category": "ClassDiagram",
      "description": "association",
      "content": "classG <-- classH",
      "sortingOrder": 6,
      "isPinned": false
    },
    {
      "id": "f5279886-6c37-425b-9959-01d18c3c0332",
      "category": "ClassDiagram",
      "description": "solid link",
      "content": "classI -- classJ",
      "sortingOrder": 7,
      "isPinned": false
    },
    {
      "id": "cade2274-3313-4197-a55f-0ed77c876a02",
      "category": "ClassDiagram",
      "description": "dependency",
      "content": "classK <.. classL",
      "sortingOrder": 8,
      "isPinned": false
    },
    {
      "id": "0733cd13-601a-4399-b001-a2ca3e8703b2",
      "category": "ClassDiagram",
      "description": "realization",
      "content": "classM <|.. classN",
      "sortingOrder": 9,
      "isPinned": false
    },
    {
      "id": "8e20efe6-41f4-4e0c-aa94-2e0a843197c5",
      "category": "ClassDiagram",
      "description": "dashed link",
      "content": "classO .. classP",
      "sortingOrder": 10,
      "isPinned": false
    },
    {
      "id": "f5753b8d-1d9e-41b8-9349-0a066c899077",
      "category": "ClassDiagram",
      "description": "two-way relation",
      "content": "Animal <|--|> Zebra",
      "sortingOrder": 11,
      "isPinned": false
    },
    {
      "id": "2dc4cb9f-49bf-47dc-bfc8-b59c2a6227ea",
      "category": "ClassDiagram",
      "description": "sample class diagram",
      "content": "classDiagram\n        Animal <|-- Duck\n        Animal <|-- Fish\n        Animal <|-- Zebra\n        Animal : +int age\n        Animal : +String gender\n        Animal: +isMammal()\n        Animal: +mate()\n        class Duck{\n            +String beakColor\n            +swim()\n            +quack()\n        }\n        class Fish{\n            -int sizeInFeet\n            -canEat()\n        }\n        class Zebra{\n            +bool is_wild\n            +run()\n        }",
      "sortingOrder": 12,
      "isPinned": false
    },
    {
      "id": "8819ba34-83e2-4a8b-aebb-aa21fdd54add",
      "category": "StateDiagram",
      "description": "a sample state diagram",
      "content": "stateDiagram-v2\n        [*] --> Still\n        Still --> [*]\n    \n        Still --> Moving\n        Moving --> Still\n        Moving --> Crash\n        Crash --> [*]",
      "sortingOrder": 0,
      "isPinned": false
    },
    {
      "id": "bf6f5578-7418-4ef1-a0ec-d456ab2ee67f",
      "category": "StateDiagram",
      "description": "a sample state diagram with left-to-right direction",
      "content": "stateDiagram-v2\n        direction LR\n        [*] --> Still\n        Still --> [*]\n    \n        Still --> Moving\n        Moving --> Still\n        Moving --> Crash\n        Crash --> [*]",
      "sortingOrder": 1,
      "isPinned": false
    },
    {
      "id": "278c956c-4155-47bc-87da-86ca54b68f20",
      "category": "StateDiagram",
      "description": "node with description",
      "content": "s2 : This is a state description",
      "sortingOrder": 2,
      "isPinned": false
    },
    {
      "id": "1ecce117-0bc5-42ba-95fc-6263d6c35ab7",
      "category": "StateDiagram",
      "description": "a transition",
      "content": "s1 --> s2",
      "sortingOrder": 3,
      "isPinned": false
    },
    {
      "id": "ac143565-cc01-4b43-ab42-b428c718aa72",
      "category": "StateDiagram",
      "description": "a transition with label",
      "content": "s1 --> s2: A transition",
      "sortingOrder": 4,
      "isPinned": false
    },
    {
      "id": "f2c732f2-d1fd-4903-9238-98c7ffdf599a",
      "category": "StateDiagram",
      "description": "composite state",
      "content": "\n        [*] --> First\n        state First {\n            [*] --> second\n            second --> [*]\n        }",
      "sortingOrder": 5,
      "isPinned": false
    },
    {
      "id": "f32b95ec-96f8-44d3-9aad-3870abd41fc6",
      "category": "StateDiagram",
      "description": "diagram with choice",
      "content": "stateDiagram-v2\n        state if_state <<choice>>\n        [*] --> IsPositive\n        IsPositive --> if_state\n        if_state --> False: if n < 0\n        if_state --> True : if n >= 0",
      "sortingOrder": 6,
      "isPinned": false
    },
    {
      "id": "da54522c-a90b-441c-b662-f7eda724f624",
      "category": "StateDiagram",
      "description": "diagram with fork",
      "content": "stateDiagram-v2\n        state fork_state <<fork>>\n          [*] --> fork_state\n          fork_state --> State2\n          fork_state --> State3\n    \n          state join_state <<join>>\n          State2 --> join_state\n          State3 --> join_state\n          join_state --> State4\n          State4 --> [*]",
      "sortingOrder": 7,
      "isPinned": false
    },
    {
      "id": "ac09f858-bc57-4c10-9da6-4e96a23b4566",
      "category": "StateDiagram",
      "description": "a diagram with concurrency",
      "content": "stateDiagram-v2\n        [*] --> Active\n    \n        state Active {\n            [*] --> NumLockOff\n            NumLockOff --> NumLockOn : EvNumLockPressed\n            NumLockOn --> NumLockOff : EvNumLockPressed\n            --\n            [*] --> CapsLockOff\n            CapsLockOff --> CapsLockOn : EvCapsLockPressed\n            CapsLockOn --> CapsLockOff : EvCapsLockPressed\n            --\n            [*] --> ScrollLockOff\n            ScrollLockOff --> ScrollLockOn : EvScrollLockPressed\n            ScrollLockOn --> ScrollLockOff : EvScrollLockPressed\n        }",
      "sortingOrder": 8,
      "isPinned": false
    },
    {
      "id": "f3a71232-3941-4d24-8e76-b1316067c3a5",
      "category": "EntityRelationshipDiagram",
      "description": "a sample entity relationship diagram",
      "content": "erDiagram\n        CUSTOMER ||--o{ ORDER : places\n        ORDER ||--|{ LINE-ITEM : contains\n        CUSTOMER }|..|{ DELIVERY-ADDRESS : uses",
      "sortingOrder": 0,
      "isPinned": false
    },
    {
      "id": "0593ac92-95ac-47d3-9141-70a12d259131",
      "category": "EntityRelationshipDiagram",
      "description": "an entity",
      "content": "    CUSTOMER {\n            string name\n            string custNumber\n            string sector\n        }",
      "sortingOrder": 1,
      "isPinned": false
    },
    {
      "id": "616e4be3-1729-42dc-b9e9-007aac8a8b3c",
      "category": "EntityRelationshipDiagram",
      "description": "one-to-many relationship",
      "content": "A ||--|{ B : label",
      "sortingOrder": 2,
      "isPinned": false
    },
    {
      "id": "5984540c-d6b4-4e25-bb57-6ab26f188ec4",
      "category": "EntityRelationshipDiagram",
      "description": "many-to-many relationship",
      "content": "A }|--|{ B : label",
      "sortingOrder": 3,
      "isPinned": false
    },
    {
      "id": "b5491620-f4ca-4e13-ba6d-224d8c874558",
      "category": "EntityRelationshipDiagram",
      "description": "one-to-one relationship",
      "content": "A ||--|| B : label",
      "sortingOrder": 4,
      "isPinned": false
    },
    {
      "id": "3b67c60f-9771-48b5-a739-5f41a5468c0f",
      "category": "EntityRelationshipDiagram",
      "description": "many-to-one relationship",
      "content": "A }|--|| B : label",
      "sortingOrder": 5,
      "isPinned": false
    },
    {
      "id": "6d5af5a0-8c69-493e-bfa4-1d9860eddb30",
      "category": "EntityRelationshipDiagram",
      "description": "zero/one-to-one relationship",
      "content": "A |o--|| B : label",
      "sortingOrder": 6,
      "isPinned": false
    },
    {
      "id": "6cce19c4-83fc-4f1b-bda6-4432da92942a",
      "category": "EntityRelationshipDiagram",
      "description": "one-to-one/zero relationship",
      "content": "A ||--o| B : label",
      "sortingOrder": 7,
      "isPinned": false
    },
    {
      "id": "e9748278-ad5f-4a2f-abeb-c446baaf226b",
      "category": "EntityRelationshipDiagram",
      "description": "zero-or-more-to-one relationship",
      "content": "A }o--|| B : label",
      "sortingOrder": 8,
      "isPinned": false
    },
    {
      "id": "d4a35a34-4e04-452b-a812-890566da9052",
      "category": "EntityRelationshipDiagram",
      "description": "one-to-zero-or-more relationship",
      "content": "A ||--o{ B : label",
      "sortingOrder": 9,
      "isPinned": false
    },
    {
      "id": "bc04d930-68dc-44b8-ba81-6a13b3e8c6e1",
      "category": "EntityRelationshipDiagram",
      "description": "zero-or-more-to-many relationship",
      "content": "A }o--|{ B : label",
      "sortingOrder": 10,
      "isPinned": false
    },
    {
      "id": "f04bf55a-93f6-440e-9a49-f36263d23388",
      "category": "EntityRelationshipDiagram",
      "description": "many-to-zero-or-more relationship",
      "content": "A }|--o{ B : label",
      "sortingOrder": 11,
      "isPinned": false
    },
    {
      "id": "7f694a38-10fe-4c78-9d17-3b64c167a1b0",
      "category": "UserJourneyDiagram",
      "description": "a sample user journey diagram",
      "content": "journey\n        title My working day\n        section Go to work\n          Make tea: 5: Me\n          Go upstairs: 3: Me\n          Do work: 1: Me, Cat\n        section Go home\n          Go downstairs: 5: Me\n          Sit down: 5: Me",
      "sortingOrder": 0,
      "isPinned": false
    },
    {
      "id": "db9fe339-0d87-4e28-8be5-ab7c5463a1b2",
      "category": "UserJourneyDiagram",
      "description": "a step in user journey",
      "content": "      Step Title: 5: ActorName",
      "sortingOrder": 1,
      "isPinned": false
    },
    {
      "id": "bb4ae433-c84b-4f56-981b-3d308f12779d",
      "category": "GanttChart",
      "description": "simple gantt chart",
      "content": "gantt\n        title A Gantt Diagram\n        dateFormat  YYYY-MM-DD\n        section Section\n        A task           :a1, 2014-01-01, 30d\n        Another task     :after a1  , 20d\n        section Another\n        Task in sec      :2014-01-12  , 12d\n        another task      : 24d",
      "sortingOrder": 0,
      "isPinned": false
    },
    {
      "id": "ccc58bc1-e29b-4992-99ab-5f360094d60d",
      "category": "GanttChart",
      "description": "rich gantt chart",
      "content": "gantt\n        dateFormat  YYYY-MM-DD\n        title       Adding GANTT diagram functionality to mermaid\n        excludes    weekends\n    \n        section A section\n        Completed task            :done,    des1, 2014-01-06,2014-01-08\n        Active task               :active,  des2, 2014-01-09, 3d\n        Future task               :         des3, after des2, 5d\n        Future task2              :         des4, after des3, 5d\n    \n        section Critical tasks\n        Completed task in the critical line :crit, done, 2014-01-06,24h\n        Implement parser and jison          :crit, done, after des1, 2d\n        Create tests for parser             :crit, active, 3d\n        Future task in critical line        :crit, 5d\n        Create tests for renderer           :2d\n        Add to mermaid                      :1d\n        Functionality added                 :milestone, 2014-01-25, 0d\n    \n        section Documentation\n        Describe gantt syntax               :active, a1, after des1, 3d\n        Add gantt diagram to demo page      :after a1  , 20h\n        Add another diagram to demo page    :doc1, after a1  , 48h\n    \n        section Last section\n        Describe gantt syntax               :after doc1, 3d\n        Add gantt diagram to demo page      :20h\n        Add another diagram to demo page    :48h",
      "sortingOrder": 1,
      "isPinned": false
    },
    {
      "id": "d45349f6-116f-4041-baef-ad336581b77b",
      "category": "GanttChart",
      "description": "milestones example",
      "content": "gantt\n        dateFormat HH:mm\n        axisFormat %H:%M\n        Initial milestone : milestone, m1, 17:49,2min\n        taska2 : 10min\n        taska3 : 5min\n        Final milestone : milestone, m2, 18:14, 2min",
      "sortingOrder": 2,
      "isPinned": false
    },
    {
      "id": "09ce5cc8-f5f8-4762-8ad1-be7b48bce463",
      "category": "PieChart",
      "description": "sample pie chart",
      "content": "pie title /r/obsidianmd posts by type\n        \"Look at my awesome graph\" : 85\n        \"Look at my cool dashboard\" : 14\n        \"Moved from Notion, liking it\" : 1",
      "sortingOrder": 0,
      "isPinned": false
    },
    {
      "id": "9b168cdf-54b9-4fce-a5da-c087f20776a2",
      "category": "PieChart",
      "description": "sample pie chart with values shown in legend",
      "content": "pie showdata\n        title /r/obsidianmd posts by type\n        \"Graphs\" : 85\n        \"Dashboards\" : 14\n        \"Tips\" : 1",
      "sortingOrder": 1,
      "isPinned": false
    },
    {
      "id": "47a4ead9-a06f-44e6-bd4a-48f2c051feaf",
      "category": "RequirementDiagram",
      "description": "sample requirements diagram",
      "content": "    requirementDiagram\n\n        requirement test_req {\n        id: 1\n        text: the test text.\n        risk: high\n        verifymethod: test\n        }\n    \n        element test_entity {\n        type: simulation\n        }\n    \n        test_entity - satisfies -> test_req",
      "sortingOrder": 0,
      "isPinned": false
    },
    {
      "id": "eb049d40-dfd1-42cf-bf42-c8a5968d75f3",
      "category": "RequirementDiagram",
      "description": "sample requirements diagram",
      "content": "element customElement {\n            type: customType\n            docref: customDocRef\n        }",
      "sortingOrder": 1,
      "isPinned": false
    },
    {
      "id": "474d843f-6bb7-44fe-ae2c-0f0bbc6a2d50",
      "category": "RequirementDiagram",
      "description": "a requirement with high risk",
      "content": "functionalRequirement myReq {\n            id: reqId\n            text: someText\n            risk: High\n            verifymethod: analysis\n        }",
      "sortingOrder": 2,
      "isPinned": false
    },
    {
      "id": "e61c2de3-dab8-4365-ba1b-97ed712b0bba",
      "category": "RequirementDiagram",
      "description": "sample requirements diagram",
      "content": "interfaceRequirement myReq2 {\n            id: reqId\n            text: someText\n            risk: Medium\n            verifymethod: demonstration\n        }",
      "sortingOrder": 3,
      "isPinned": false
    },
    {
      "id": "69fa1a5b-d994-42ba-babe-60503847a5c9",
      "category": "RequirementDiagram",
      "description": "sample requirements diagram",
      "content": "designConstraint myReq3 {\n            id: reqId\n            text: someText\n            risk: Low\n            verifymethod: test\n        }",
      "sortingOrder": 4,
      "isPinned": false
    },
    {
      "id": "1525076c-b669-487f-9bdd-0714d322531e",
      "category": "GitGraph",
      "description": "simple git graph",
      "content": "gitGraph\n        commit\n        commit\n        branch develop\n        checkout develop\n        commit\n        commit\n        checkout main\n        merge develop\n        commit\n        commit",
      "sortingOrder": 0,
      "isPinned": false
    },
    {
      "id": "d1a8275a-d2e9-4b92-b086-5e55f355c46c",
      "category": "GitGraph",
      "description": "tagged commit",
      "content": "commit id: \"Normal\" tag: \"v1.0.0\"",
      "sortingOrder": 1,
      "isPinned": false
    },
    {
      "id": "7ee4a8a1-5e5e-4a1a-960e-df2e070992c5",
      "category": "GitGraph",
      "description": "reverse commit",
      "content": "commit id: \"Reverse\" type: REVERSE",
      "sortingOrder": 2,
      "isPinned": false
    },
    {
      "id": "9d4dc12e-d725-42db-a883-b22af8f6a61c",
      "category": "GitGraph",
      "description": "highlighted commit",
      "content": "commit id: \"Highlight\" type: HIGHLIGHT",
      "sortingOrder": 3,
      "isPinned": false
    },
    {
      "id": "a9207783-9ce8-4932-9725-872ac38ded84",
      "category": "GitGraph",
      "description": "reverse commit",
      "content": "commit id: \"Reverse\" type: REVERSE",
      "sortingOrder": 4,
      "isPinned": false
    },
    {
      "id": "66aee8f1-792f-4779-a8ba-c6c49b46ec5f",
      "category": "GitGraph",
      "description": "git graph with cherry-pick",
      "content": "gitGraph\n        commit id: \"ZERO\"\n        branch develop\n        commit id:\"A\"\n        checkout main\n        commit id:\"ONE\"\n        checkout develop\n        commit id:\"B\"\n        checkout main\n        commit id:\"TWO\"\n        cherry-pick id:\"A\"\n        commit id:\"THREE\"\n        checkout develop\n        commit id:\"C\"",
      "sortingOrder": 5,
      "isPinned": false
    }
  ],
  "selectedCategory": "GanttChart"
}